outetts/__init__.py
outetts/interface.py
outetts/anyascii/__init__.py
outetts/anyascii/_data/000
outetts/anyascii/_data/001
outetts/anyascii/_data/002
outetts/anyascii/_data/003
outetts/anyascii/_data/004
outetts/anyascii/_data/005
outetts/anyascii/_data/006
outetts/anyascii/_data/007
outetts/anyascii/_data/008
outetts/anyascii/_data/009
outetts/anyascii/_data/00a
outetts/anyascii/_data/00b
outetts/anyascii/_data/00c
outetts/anyascii/_data/00d
outetts/anyascii/_data/00e
outetts/anyascii/_data/00f
outetts/anyascii/_data/010
outetts/anyascii/_data/011
outetts/anyascii/_data/012
outetts/anyascii/_data/013
outetts/anyascii/_data/014
outetts/anyascii/_data/015
outetts/anyascii/_data/016
outetts/anyascii/_data/017
outetts/anyascii/_data/018
outetts/anyascii/_data/019
outetts/anyascii/_data/01a
outetts/anyascii/_data/01b
outetts/anyascii/_data/01c
outetts/anyascii/_data/01d
outetts/anyascii/_data/01e
outetts/anyascii/_data/01f
outetts/anyascii/_data/020
outetts/anyascii/_data/021
outetts/anyascii/_data/022
outetts/anyascii/_data/023
outetts/anyascii/_data/024
outetts/anyascii/_data/025
outetts/anyascii/_data/026
outetts/anyascii/_data/027
outetts/anyascii/_data/028
outetts/anyascii/_data/029
outetts/anyascii/_data/02a
outetts/anyascii/_data/02b
outetts/anyascii/_data/02c
outetts/anyascii/_data/02d
outetts/anyascii/_data/02e
outetts/anyascii/_data/02f
outetts/anyascii/_data/030
outetts/anyascii/_data/031
outetts/anyascii/_data/032
outetts/anyascii/_data/033
outetts/anyascii/_data/034
outetts/anyascii/_data/035
outetts/anyascii/_data/036
outetts/anyascii/_data/037
outetts/anyascii/_data/038
outetts/anyascii/_data/039
outetts/anyascii/_data/03a
outetts/anyascii/_data/03b
outetts/anyascii/_data/03c
outetts/anyascii/_data/03d
outetts/anyascii/_data/03e
outetts/anyascii/_data/03f
outetts/anyascii/_data/040
outetts/anyascii/_data/041
outetts/anyascii/_data/042
outetts/anyascii/_data/043
outetts/anyascii/_data/044
outetts/anyascii/_data/045
outetts/anyascii/_data/046
outetts-0.4.4.dist-info/LICENSE
outetts-0.4.4.dist-info/METADATA
outetts-0.4.4.dist-info/WHEEL
outetts-0.4.4.dist-info/top_level.txt
outetts-0.4.4.dist-info/RECORD
