Metadata-Version: 2.1
Name: outetts
Version: 0.4.4
Summary: OuteAI Text-to-Speech (TTS)
Home-page: https://github.com/edwko/OuteTTS
Author: OuteAI
Classifier: Programming Language :: Python :: 3
Classifier: License :: OSI Approved :: Apache Software License
Classifier: Operating System :: OS Independent
Requires-Python: >=3.10
License-File: LICENSE
Requires-Dist: llama-cpp-python==0.3.9
Requires-Dist: torch
Requires-Dist: torchvision
Requires-Dist: torchaudio
Requires-Dist: scipy
Requires-Dist: einops
Requires-Dist: pyyaml
Requires-Dist: huggingface-hub
Requires-Dist: encodec
Requires-Dist: matplotlib
Requires-Dist: transformers==4.52.3
Requires-Dist: soundfile
Requires-Dist: numpy
Requires-Dist: inflect
Requires-Dist: loguru
Requires-Dist: polars
Requires-Dist: natsort
Requires-Dist: tqdm
Requires-Dist: requests
Requires-Dist: sounddevice
Requires-Dist: mecab-python3
Requires-Dist: unidic-lite
Requires-Dist: uroman
Requires-Dist: openai-whisper>=20240930
Requires-Dist: pygame
Requires-Dist: descript-audio-codec
Requires-Dist: aiohttp
Requires-Dist: ftfy
